dicom_cnn/__init__.py
dicom_cnn/exceptions/__init__.py
dicom_cnn/exceptions/dicom_exceptions.py
dicom_cnn/instance/__init__.py
dicom_cnn/instance/dicom_enums.py
dicom_cnn/instance/dicom_instance.py
dicom_cnn/instance/rtss.py
dicom_cnn/instance/tag_decorators.py
dicom_cnn/orthanc/__init__.py
dicom_cnn/orthanc/apis.py
dicom_cnn/petctviewer/__init__.py
dicom_cnn/petctviewer/csv_reader.py
dicom_cnn/petctviewer/csv_to_nifti.py
dicom_cnn/petctviewer/csv_volume.py
dicom_cnn/petctviewer/mask_builder.py
dicom_cnn/petctviewer/rois/__init__.py
dicom_cnn/petctviewer/rois/roi.py
dicom_cnn/petctviewer/rois/roi_elipse.py
dicom_cnn/petctviewer/rois/roi_factory.py
dicom_cnn/petctviewer/rois/roi_nifti.py
dicom_cnn/petctviewer/rois/roi_polygon.py
dicom_cnn/processing/__init__.py
dicom_cnn/processing/fusion.py
dicom_cnn/processing/mip_generator.py
dicom_cnn/processing/radiomics.py
dicom_cnn/processing/utils.py
dicom_cnn/processing/watershed.py
dicom_cnn/reader/__init__.py
dicom_cnn/reader/abstract_dicom_reader.py
dicom_cnn/reader/dicom_instance_file_reader.py
dicom_cnn/reader/dicom_instance_orthanc_reader.py
dicom_cnn/reader/dicom_series_file_reader.py
dicom_cnn/reader/nifti_reader.py
dicom_cnn/series/__init__.py
dicom_cnn/series/series.py
dicom_cnn/series/series_pt.py
dicom_cnn/study/__init__.py
dicom_cnn/study/study.py
dicom_cnn/writer/__init__.py
dicom_cnn/writer/series_exporter.py
dicom_cnn/writer/series_exporter_PT.py
dicom_cnn-0.1.4.dist-info/LICENSE
dicom_cnn-0.1.4.dist-info/METADATA
dicom_cnn-0.1.4.dist-info/WHEEL
dicom_cnn-0.1.4.dist-info/top_level.txt
dicom_cnn-0.1.4.dist-info/RECORD
