Metadata-Version: 2.1
Name: dicom-cnn
Version: 0.1.4
Summary: Librairie to sort - process dicom to feed CNN models
Home-page: https://github.com/Pixilib/dicom_cnn
Author: Pixilib
Requires-Python: ~=3.9
License-File: LICENSE
Requires-Dist: certifi (==2022.9.24)
Requires-Dist: charset-normalizer (==2.1.1)
Requires-Dist: contourpy (==1.0.6)
Requires-Dist: cycler (==0.11.0)
Requires-Dist: fonttools (==4.38.0)
Requires-Dist: idna (==3.4)
Requires-Dist: imageio (==2.22.4)
Requires-Dist: kiwisolver (==1.4.4)
Requires-Dist: matplotlib (==3.6.2)
Requires-Dist: networkx (==2.8.8)
Requires-Dist: numpy (==1.23.5)
Requires-Dist: packaging (==21.3)
Requires-Dist: pillow (==9.3.0)
Requires-Dist: pydicom (==1.4.2)
Requires-Dist: pyparsing (==3.0.9)
Requires-Dist: python-dateutil (==2.8.2)
Requires-Dist: pywavelets (==1.4.1)
Requires-Dist: requests (==2.28.1)
Requires-Dist: scikit-image (==0.19.3)
Requires-Dist: scipy (==1.9.3)
Requires-Dist: simpleitk (==2.2.0)
Requires-Dist: six (==1.16.0)
Requires-Dist: tifffile (==2022.10.10)
Requires-Dist: typing-extensions (==4.4.0)
Requires-Dist: urllib3 (==1.26.13)
